whatimiss/__init__.py
whatimiss/decorator/__init__.py
whatimiss/decorator/func_decorator.py
whatimiss/func_utils/__init__.py
whatimiss-0.0.1.dist-info/METADATA
whatimiss-0.0.1.dist-info/WHEEL
whatimiss-0.0.1.dist-info/top_level.txt
whatimiss-0.0.1.dist-info/RECORD
