Metadata-Version: 2.1
Name: whatimiss
Version: 0.0.1
Summary: 打包示例
Home-page: https://github.com/zhangminvip
Author: zhangmin
Author-email: a991391009@gmail.com
License: UNKNOWN
Platform: UNKNOWN
Classifier: Programming Language :: Python :: 3
Classifier: License :: OSI Approved :: MIT License
Classifier: Operating System :: OS Independent
Requires-Python: >=3.6
